nbformat/__init__.py
nbformat/_imports.py
nbformat/_struct.py
nbformat/_version.py
nbformat/converter.py
nbformat/current.py
nbformat/json_compat.py
nbformat/notebooknode.py
nbformat/py.typed
nbformat/reader.py
nbformat/sentinel.py
nbformat/sign.py
nbformat/validator.py
nbformat/warnings.py
nbformat/corpus/__init__.py
nbformat/corpus/words.py
nbformat/corpus/tests/__init__.py
nbformat/corpus/tests/test_words.py
nbformat/v1/__init__.py
nbformat/v1/convert.py
nbformat/v1/nbbase.py
nbformat/v1/nbjson.py
nbformat/v1/rwbase.py
nbformat/v2/__init__.py
nbformat/v2/convert.py
nbformat/v2/nbbase.py
nbformat/v2/nbjson.py
nbformat/v2/nbpy.py
nbformat/v2/nbxml.py
nbformat/v2/rwbase.py
nbformat/v3/__init__.py
nbformat/v3/convert.py
nbformat/v3/nbbase.py
nbformat/v3/nbformat.v3.schema.json
nbformat/v3/nbjson.py
nbformat/v3/nbpy.py
nbformat/v3/rwbase.py
nbformat/v4/__init__.py
nbformat/v4/convert.py
nbformat/v4/nbbase.py
nbformat/v4/nbformat.v4.0.schema.json
nbformat/v4/nbformat.v4.1.schema.json
nbformat/v4/nbformat.v4.2.schema.json
nbformat/v4/nbformat.v4.3.schema.json
nbformat/v4/nbformat.v4.4.schema.json
nbformat/v4/nbformat.v4.5.schema.json
nbformat/v4/nbformat.v4.schema.json
nbformat/v4/nbjson.py
nbformat/v4/rwbase.py
nbformat-5.10.1.dist-info/METADATA
nbformat-5.10.1.dist-info/WHEEL
nbformat-5.10.1.dist-info/entry_points.txt
nbformat-5.10.1.dist-info/licenses/LICENSE
nbformat-5.10.1.dist-info/RECORD
