Metadata-Version: 2.1
Name: nbformat
Version: 5.10.1
Summary: The Jupyter Notebook format
Project-URL: Homepage, https://jupyter.org
Project-URL: Changelog, https://github.com/jupyter/nbformat/blob/main/CHANGELOG.md
Project-URL: Documentation, https://nbformat.readthedocs.io/
Project-URL: Repository, https://github.com/jupyter/nbformat.git
Author-email: Jupyter Development Team <jupyter@googlegroups.com>
License: BSD 3-Clause License
License-File: LICENSE
Keywords: Interactive,Interpreter,Shell,Web
Classifier: Intended Audience :: Developers
Classifier: Intended Audience :: Science/Research
Classifier: Intended Audience :: System Administrators
Classifier: License :: OSI Approved :: BSD License
Classifier: Programming Language :: Python
Classifier: Programming Language :: Python :: 3
Classifier: Programming Language :: Python :: 3.8
Classifier: Programming Language :: Python :: 3.9
Classifier: Programming Language :: Python :: 3.10
Classifier: Programming Language :: Python :: 3.11
Classifier: Programming Language :: Python :: 3.12
Requires-Python: >=3.8
Requires-Dist: fastjsonschema
Requires-Dist: jsonschema>=2.6
Requires-Dist: jupyter-core
Requires-Dist: traitlets>=5.1
Provides-Extra: docs
Requires-Dist: myst-parser; extra == 'docs'
Requires-Dist: pydata-sphinx-theme; extra == 'docs'
Requires-Dist: sphinx; extra == 'docs'
Requires-Dist: sphinxcontrib-github-alt; extra == 'docs'
Requires-Dist: sphinxcontrib-spelling; extra == 'docs'
Provides-Extra: test
Requires-Dist: pep440; extra == 'test'
Requires-Dist: pre-commit; extra == 'test'
Requires-Dist: pytest; extra == 'test'
Requires-Dist: testpath; extra == 'test'
